satif_core/__init__.py
satif_core/adapters/__init__.py
satif_core/adapters/base.py
satif_core/code_executors/__init__.py
satif_core/code_executors/_exceptions.py
satif_core/code_executors/base.py
satif_core/comparators/__init__.py
satif_core/comparators/base.py
satif_core/exceptions.py
satif_core/representers/__init__.py
satif_core/representers/base.py
satif_core/sdif_db.py
satif_core/standardizers/__init__.py
satif_core/standardizers/base.py
satif_core/transformation_builders/__init__.py
satif_core/transformation_builders/base.py
satif_core/transformers/__init__.py
satif_core/transformers/base.py
satif_core/types.py
satif_core-0.3.1.dist-info/LICENSE
satif_core-0.3.1.dist-info/METADATA
satif_core-0.3.1.dist-info/WHEEL
satif_core-0.3.1.dist-info/entry_points.txt
satif_core-0.3.1.dist-info/RECORD
