Metadata-Version: 2.3
Name: satif-core
Version: 0.3.1
Summary: Core SDK for AI Agents
License: MIT
Author: Syncpulse
Maintainer: Bryan Djafer
Maintainer-email: bryan.djafer@syncpulse.fr
Requires-Python: >=3.9,<4.0
Classifier: License :: OSI Approved :: MIT License
Classifier: Programming Language :: Python :: 3
Classifier: Programming Language :: Python :: 3.9
Classifier: Programming Language :: Python :: 3.10
Classifier: Programming Language :: Python :: 3.11
Classifier: Programming Language :: Python :: 3.12
Classifier: Programming Language :: Python :: 3.13
